{
  "Native": {
    "bmt_aos.O3": {
      "M": [
        [
          6888.768246,
          20.033052682876587
        ],
        [
          6889.183964,
          20.029812335968018
        ],
        [
          6905.503662,
          19.983320951461792
        ]
      ],
      "L": [
        [
          6872.376511,
          17.209481954574585
        ],
        [
          6906.338158,
          17.13052463531494
        ],
        [
          7014.054348,
          16.882763862609863
        ]
      ],
      "XL": [
        [
          6851.136447,
          19.055731534957886
        ],
        [
          6845.696487,
          19.19601559638977
        ],
        [
          6815.506161,
          19.382718801498413
        ]
      ]
    },
    "matrix": {
      "256": [
        [
          0.012037,
          0.012836,
          0.03282332420349121
        ],
        [
          0.012065,
          0.012728,
          0.031679630279541016
        ],
        [
          0.011986,
          0.012768,
          0.031392812728881836
        ]
      ],
      "512": [
        [
          0.109203,
          0.088447,
          0.2058238983154297
        ],
        [
          0.108013,
          0.088246,
          0.20403242111206055
        ],
        [
          0.108688,
          0.088217,
          0.20467734336853027
        ]
      ],
      "1024": [
        [
          5.575759,
          0.684557,
          6.271738767623901
        ],
        [
          5.551076,
          0.681335,
          6.24293065071106
        ],
        [
          5.532918,
          0.680541,
          6.223728895187378
        ]
      ]
    }
  },
  "CIG": {
    "bmt_aos.O3": {
      "M": [
        [
          26.266487,
          5238.176830530167
        ],
        [
          26.16239,
          5259.04855632782
        ],
        [
          26.189007,
          5253.220917701721
        ]
      ],
      "L": [
        [
          24.522347,
          4702.3030564785
        ],
        [
          24.425419,
          4720.8541712760925
        ],
        [
          24.491357,
          4707.115206956863
        ]
      ],
      "XL": [
        [
          23.929097,
          4933.517940282822
        ],
        [
          23.921676,
          4932.550156831741
        ],
        [
          23.742312,
          4967.734417676926
        ]
      ]
    },
    "matrix": {
      "256": [
        [
          1.96832,
          1.439139,
          5.269315481185913
        ],
        [
          1.951089,
          1.43268,
          3.686579465866089
        ],
        [
          1.972283,
          1.441293,
          3.6964468955993652
        ]
      ],
      "512": [
        [
          20.731834,
          10.107934,
          31.189949989318848
        ],
        [
          20.912444,
          10.191888,
          31.45475172996521
        ],
        [
          20.871331,
          10.205605,
          31.426435232162476
        ]
      ],
      "1024": [
        [
          391.765705,
          99.167774,
          491.5643274784088
        ],
        [
          391.106478,
          99.051704,
          492.12863969802856
        ],
        [
          390.735526,
          99.25196,
          490.61616492271423
        ]
      ]
    }
  }
}